CHANGES.rst
DESCRIPTION.rst
LICENSE
MANIFEST.in
README.md
setup.py
src/wai.annotations.grayscale.egg-info/PKG-INFO
src/wai.annotations.grayscale.egg-info/SOURCES.txt
src/wai.annotations.grayscale.egg-info/dependency_links.txt
src/wai.annotations.grayscale.egg-info/entry_points.txt
src/wai.annotations.grayscale.egg-info/namespace_packages.txt
src/wai.annotations.grayscale.egg-info/requires.txt
src/wai.annotations.grayscale.egg-info/top_level.txt
src/wai/annotations/grayscale/__init__.py
src/wai/annotations/grayscale/component/_FromGrayscale.py
src/wai/annotations/grayscale/component/_GrayscaleReader.py
src/wai/annotations/grayscale/component/_GrayscaleWriter.py
src/wai/annotations/grayscale/component/_ToGrayscale.py
src/wai/annotations/grayscale/component/__init__.py
src/wai/annotations/grayscale/specifier/_GrayscaleInputFormatSpecifier.py
src/wai/annotations/grayscale/specifier/_GrayscaleOutputFormatSpecifier.py
src/wai/annotations/grayscale/specifier/__init__.py
src/wai/annotations/grayscale/util/__init__.py
src/wai/annotations/grayscale/util/_format.py